graiax/nem/__init__.py
graiax/nem/elements.py
graiax/nem/filter.py
graiax/nem/filters.py
graiax/nem/nem.py
graiax/nem/permission.py
graiax/nem/utils.py
graiax_nem-0.0.4.dev6.dist-info/LICENSE
graiax_nem-0.0.4.dev6.dist-info/METADATA
graiax_nem-0.0.4.dev6.dist-info/WHEEL
graiax_nem-0.0.4.dev6.dist-info/top_level.txt
graiax_nem-0.0.4.dev6.dist-info/RECORD
