Metadata-Version: 2.1
Name: graiax-nem
Version: 0.0.4.dev6
Summary: 适用于 Graia Framework 的消息解析过滤器
Home-page: https://github.com/jinzhijie/graiax-nem
Author: Xiao_Jin
License: UNKNOWN
Keywords: graia graiax nem graiax-nem graia-message
Platform: UNKNOWN
Requires-Python: >=3.7
Requires-Dist: graia-application-mirai
